pyqlc/__init__.py
pyqlc/_work_avx.cp38-win_amd64.pyd
pyqlc/_work_ref.cp38-win_amd64.pyd
pyqlc/_work_sse2.cp38-win_amd64.pyd
pyqlc/_work_sse4_1.cp38-win_amd64.pyd
pyqlc/_work_ssse3.cp38-win_amd64.pyd
pyqlc/account.py
pyqlc/client.py
pyqlc/contract.py
pyqlc/destroy.py
pyqlc/dodsettlement.py
pyqlc/dpki.py
pyqlc/kyc.py
pyqlc/ledger.py
pyqlc/miner.py
pyqlc/mintage.py
pyqlc/net.py
pyqlc/permission.py
pyqlc/pledge.py
pyqlc/pov.py
pyqlc/ptmkey.py
pyqlc/pub_sub.py
pyqlc/representation.py
pyqlc/rewards.py
pyqlc/settlement.py
pyqlc/util.py
pyqlc/utils/__init__.py
pyqlc/utils/block.py
pyqlc/utils/crypto.py
pyqlc/utils/exceptions.py
pyqlc/utils/helper.py
pyqlc/utils/work.py
pyqlc-0.0.3.dist-info/LICENSE
pyqlc-0.0.3.dist-info/METADATA
pyqlc-0.0.3.dist-info/WHEEL
pyqlc-0.0.3.dist-info/top_level.txt
pyqlc-0.0.3.dist-info/RECORD
