Metadata-Version: 2.1
Name: pyqlc
Version: 0.0.3
Summary: Python SDK for interacting with QLC node
Home-page: https://github.com/realForbis/qlc-python-SDK
Author: Lukáš Heczko
Author-email: heczkolukas@protonmail.com
License: MIT
Platform: UNKNOWN
Classifier: Programming Language :: Python
Classifier: Programming Language :: Python :: 3
Classifier: Programming Language :: Python :: 3.6
Classifier: Programming Language :: Python :: 3.7
Classifier: Programming Language :: Python :: Implementation :: CPython
Classifier: Operating System :: Microsoft :: Windows
Classifier: Operating System :: POSIX :: Linux
Classifier: Topic :: Office/Business :: Financial
Requires-Python: >=3.6.0
Requires-Dist: ed25519-blake2b (>=1.4)
Requires-Dist: py-cpuinfo (>=4)
Requires-Dist: requests
